{
  "Library": "_Interface_Expansion",
  "Reference": "U",
  "Symbol": "Robast:PCA9535PW,118",
  "Value": "PCA9535PW,118",
  "Footprint": "Package_SO:TSSOP-24_4.4x7.8mm_P0.65mm",
  "Description": "16xI/O Expander 400kHz TSSOP-24",
  "Datasheet": "https://www.nxp.com/docs/en/data-sheet/PCA9535_PCA9535C.pdf",
  "Keywords": "I/O Expander",
  "CustomFields": {
    "MF": "NXP Semicon",
    "MPN": "PCA9535PW,118",
    "OC_LCSC": "C255606",
    "OC_MOUSER": "",
    "OC_RS": "",
    "OC_CONRAD": "",
    "path_to_docs": "Semiconductors/Interface_ICs/IO-Expander/NXP"
  }
}